LICENSE.txt
README.md
setup.cfg
setup.py
STEP/Cleaner.py
STEP/Converter.py
STEP/Helper.py
STEP/IdentityCache.py
STEP/REST.py
STEP/SOAP.py
STEP/XML.py
STEP/XSD.py
STEP/__init__.py
STEP.py.egg-info/PKG-INFO
STEP.py.egg-info/SOURCES.txt
STEP.py.egg-info/dependency_links.txt
STEP.py.egg-info/requires.txt
STEP.py.egg-info/top_level.txt
bin/converter.py
bin/excel2step.py
bin/step.rest.py
bin/step.soap.py
bin/step2uml.py
bin/uml2step.py
test/test_rest.py