Metadata-Version: 2.2
Name: STEP.py
Version: 2.50
Home-page: https://github.com/eddo888/STEP.py
Download-URL: https://github.com/eddo888/STEP.py/archive/2.50.tar.gz
Author: David Edson
Author-email: eddo888@tpg.com.au
License: MIT
License-File: LICENSE.txt
Requires-Dist: argcomplete
Requires-Dist: openpyxl
Requires-Dist: xlrd
Requires-Dist: xlwt
Requires-Dist: dotmap
Requires-Dist: pyxb-x
Requires-Dist: suds-py3
Requires-Dist: xmltodict
Requires-Dist: Baubles
Requires-Dist: Perdy
Requires-Dist: Argumental
Requires-Dist: GoldenChild
Requires-Dist: Swapsies
Dynamic: author
Dynamic: author-email
Dynamic: description
Dynamic: description-content-type
Dynamic: download-url
Dynamic: home-page
Dynamic: license
Dynamic: requires-dist
